openai_types/__init__.py
openai_types/_models.py
openai_types/audio_model.py
openai_types/audio_response_format.py
openai_types/auto_file_chunking_strategy_param.py
openai_types/batch.py
openai_types/batch_create_params.py
openai_types/batch_error.py
openai_types/batch_list_params.py
openai_types/batch_request_counts.py
openai_types/chat_model.py
openai_types/completion.py
openai_types/completion_choice.py
openai_types/completion_create_params.py
openai_types/completion_usage.py
openai_types/container_create_params.py
openai_types/container_create_response.py
openai_types/container_list_params.py
openai_types/container_list_response.py
openai_types/container_retrieve_response.py
openai_types/create_embedding_response.py
openai_types/embedding.py
openai_types/embedding_create_params.py
openai_types/embedding_model.py
openai_types/eval_create_params.py
openai_types/eval_create_response.py
openai_types/eval_custom_data_source_config.py
openai_types/eval_delete_response.py
openai_types/eval_list_params.py
openai_types/eval_list_response.py
openai_types/eval_retrieve_response.py
openai_types/eval_stored_completions_data_source_config.py
openai_types/eval_update_params.py
openai_types/eval_update_response.py
openai_types/file_chunking_strategy.py
openai_types/file_chunking_strategy_param.py
openai_types/file_content.py
openai_types/file_create_params.py
openai_types/file_deleted.py
openai_types/file_list_params.py
openai_types/file_object.py
openai_types/file_purpose.py
openai_types/image.py
openai_types/image_create_variation_params.py
openai_types/image_edit_completed_event.py
openai_types/image_edit_params.py
openai_types/image_edit_partial_image_event.py
openai_types/image_edit_stream_event.py
openai_types/image_gen_completed_event.py
openai_types/image_gen_partial_image_event.py
openai_types/image_gen_stream_event.py
openai_types/image_generate_params.py
openai_types/image_model.py
openai_types/images_response.py
openai_types/model.py
openai_types/model_deleted.py
openai_python_types-1.107.2.dist-info/METADATA
openai_python_types-1.107.2.dist-info/WHEEL
openai_python_types-1.107.2.dist-info/top_level.txt
openai_python_types-1.107.2.dist-info/RECORD
