Metadata-Version: 2.4
Name: openai-python-types
Version: 1.107.2
Summary: Lightweight package exposing only OpenAI's Python types as `openai_types`
Project-URL: Homepage, https://github.com/zbirenbaum/openai-python-types
Project-URL: Repository, https://github.com/zbirenbaum/openai-python-types
Requires-Python: >=3.8
Requires-Dist: typing-extensions>=4.11
Requires-Dist: pydantic<3,>=1.9.0
Requires-Dist: tomli
